querytograph/__init__.py
querytograph/querytograph.py
querytograph-0.0.5.dist-info/LICENSE
querytograph-0.0.5.dist-info/METADATA
querytograph-0.0.5.dist-info/WHEEL
querytograph-0.0.5.dist-info/top_level.txt
querytograph-0.0.5.dist-info/RECORD
