Metadata-Version: 2.1
Name: querytograph
Version: 0.0.5
Summary: Using ChatGPT to convert your plain English queries into graphs
Home-page: https://github.com/franziss/querytograph
Author: franziss
Author-email: franziss@gmail.com
License: MIT
Platform: UNKNOWN
License-File: LICENSE
Requires-Dist: pandas
Requires-Dist: openai
Requires-Dist: langchain (==0.0.160)
Requires-Dist: rapidfuzz (==3.0.0)
Requires-Dist: gradio (==3.26.0)
Requires-Dist: numpy
Requires-Dist: plotly
Requires-Dist: matplotlib
